chat_factory/__init__.py
chat_factory/async_chat_factory.py
chat_factory/async_models.py
chat_factory/chat_factory.py
chat_factory/models.py
chat_factory/utils/SCHEMA_FIX_SUMMARY.md
chat_factory/utils/__init__.py
chat_factory/utils/factory.py
chat_factory/utils/mcp.py
chat_factory/utils/models.py
chat_factory/utils/schema.py
llm_chat_factory-0.1.0.dist-info/METADATA
llm_chat_factory-0.1.0.dist-info/WHEEL
llm_chat_factory-0.1.0.dist-info/entry_points.txt
llm_chat_factory-0.1.0.dist-info/licenses/LICENSE
llm_chat_factory-0.1.0.dist-info/RECORD
