Metadata-Version: 2.4
Name: llm-chat-factory
Version: 0.1.0
Summary: A short description of the project
License-File: LICENSE
Author: Antonio Pisani
Author-email: antonio.pisani@gmail.com
Requires-Python: >=3.10
Classifier: Programming Language :: Python :: 3
Classifier: Programming Language :: Python :: 3.10
Classifier: Programming Language :: Python :: 3.11
Classifier: Programming Language :: Python :: 3.12
Classifier: Programming Language :: Python :: 3.13
Classifier: Programming Language :: Python :: 3.14
Requires-Dist: anthropic (>=0.75.0,<0.76.0)
Requires-Dist: gradio (>=6.3.0,<7.0.0)
Requires-Dist: mcp-multi-server (>=1.1.0,<2.0.0)
Requires-Dist: openai (>=2.15.0,<3.0.0)
Requires-Dist: pillow (>=12.1.0,<13.0.0)
Requires-Dist: pydantic (>=2.12.5,<3.0.0)
Requires-Dist: pypdf (>=6.6.0,<7.0.0)
Requires-Dist: python-dotenv (>=1.2.1,<2.0.0)
Requires-Dist: rich (>=14.2.0,<15.0.0)
Requires-Dist: sounddevice (>=0.5.3,<0.6.0)
Requires-Dist: types-requests (>=2.32.4.20260107,<3.0.0.0)
Project-URL: Documentation, https://chat-factory.readthedocs.io/
Project-URL: Issue Tracker, https://github.com/apisani1/chat-factory/issues
Project-URL: Release Notes, https://github.com/apisani1/chat-factory/releases
Project-URL: Source Code, https://github.com/apisani1/chat-factory
